e_commerce_scraper/__init__.py
e_commerce_scraper/_version.py
e_commerce_scraper/logging.py
e_commerce_scraper/main.py
e_commerce_scraper/scraper.py
e_commerce_scraper/utils.py
e_commerce_scraper/config/__init__.py
e_commerce_scraper/config/base.py
e_commerce_scraper/config/defaults.py
e_commerce_scraper/config/loaders.py
e_commerce_scraper/config/mappers.py
e_commerce_scraper/config/utils.py
e_commerce_scraper/libs/__init__.py
e_commerce_scraper/libs/linux/__init__.py
e_commerce_scraper/libs/linux/chromedriver
e_commerce_scraper/libs/linux/chromedriver.exe
e_commerce_scraper/libs/win32/__init__.py
e_commerce_scraper/libs/win32/chromedriver.exe
e_commerce_scraper/logs/__init__.py
e_commerce_scraper/mixins/__init__.py
e_commerce_scraper/mixins/from_mytek.py
e_commerce_scraper/mixins/from_spacenet.py
e_commerce_scraper/mixins/from_tunisianet.py
e_commerce_scraper/mixins/from_zoom.py
e_commerce_scraper/mixins/utils.py
e_commerce_scraper-0.1.0.dist-info/METADATA
e_commerce_scraper-0.1.0.dist-info/WHEEL
e_commerce_scraper-0.1.0.dist-info/top_level.txt
e_commerce_scraper-0.1.0.dist-info/RECORD
